memg/__init__.py
memg/ai/README_GEMINI_EMBEDDING.md
memg/ai/__init__.py
memg/ai/embedder_factory.py
memg/ai/gemini_embedder.py
memg/ai/genai.py
memg/api/__init__.py
memg/api/enhanced_search.py
memg/core/__init__.py
memg/search/__init__.py
memg/search/orchestrator.py
memg/utils/__init__.py
memg/utils/schema.py
memg-0.5.8.dist-info/licenses/LICENSE
memg-0.5.8.dist-info/METADATA
memg-0.5.8.dist-info/WHEEL
memg-0.5.8.dist-info/top_level.txt
memg-0.5.8.dist-info/RECORD
