Metadata-Version: 2.4
Name: memg
Version: 0.5.8
Summary: True memory for AI - lightweight, generalist, AI-made, AI-focused
Author-email: GenovoAI Team <info@genovoai.com>
License: MIT
Project-URL: Homepage, https://github.com/genovo-ai/memg
Project-URL: Repository, https://github.com/genovo-ai/memg.git
Project-URL: Issues, https://github.com/genovo-ai/memg/issues
Project-URL: Documentation, https://github.com/genovo-ai/memg#readme
Keywords: ai,memory,agents,search,memg,artificial-intelligence,knowledge-management,semantic-search
Classifier: Development Status :: 4 - Beta
Classifier: Intended Audience :: Developers
Classifier: Intended Audience :: Science/Research
Classifier: License :: OSI Approved :: MIT License
Classifier: Operating System :: OS Independent
Classifier: Programming Language :: Python :: 3
Classifier: Programming Language :: Python :: 3.11
Classifier: Programming Language :: Python :: 3.12
Classifier: Programming Language :: Python :: 3.13
Classifier: Topic :: Scientific/Engineering :: Artificial Intelligence
Classifier: Topic :: Software Development :: Libraries :: Python Modules
Classifier: Topic :: Database :: Database Engines/Servers
Classifier: Typing :: Typed
Requires-Python: >=3.11
License-File: LICENSE
Requires-Dist: memg-core>=0.5.2
Requires-Dist: google-genai==1.30.0
Requires-Dist: python-dotenv>=1.1.0
Requires-Dist: pydantic>=2.11.0
Requires-Dist: pandas>=2.3.1
Requires-Dist: tabulate>=0.9.0
Provides-Extra: dev
Requires-Dist: pytest>=8.4.1; extra == "dev"
Requires-Dist: pytest-cov>=6.2.1; extra == "dev"
Requires-Dist: pytest-asyncio>=0.23.8; extra == "dev"
Requires-Dist: psutil>=5.9.8; extra == "dev"
Requires-Dist: ruff>=0.12.0; extra == "dev"
Requires-Dist: mypy>=1.17.0; extra == "dev"
Requires-Dist: bandit[toml]>=1.8.0; extra == "dev"
Requires-Dist: pre-commit>=4.0.0; extra == "dev"
Provides-Extra: all
Requires-Dist: memg[dev]; extra == "all"
Dynamic: license-file
